code_qfire/__init__.py
code_qfire/main.py
code_qfire-0.1.0.dist-info/METADATA
code_qfire-0.1.0.dist-info/WHEEL
code_qfire-0.1.0.dist-info/entry_points.txt
code_qfire-0.1.0.dist-info/top_level.txt
code_qfire-0.1.0.dist-info/RECORD
